{
  "venue": "京都",
  "updated": "2026-01-06",
  "format_version": "detailed_v1",
  "courses": [
    {
      "course": {
        "name": "京都芝1200m（内回り）",
        "racecourse": "京都",
        "surface": "芝",
        "distance_m": 1200
      },
      "course_structure": {
        "overview": "向正面直線の半ば付近からスタートし、最初のコーナーまで約320m。4コーナーからゴールまでの直線はAコース328.4m、B・C・Dコース323.4mと短い。",
        "elevation": "コース全体の高低差は3.1m（改修後4.3m説あり）。スタート直後から3コーナー途中まで上り坂、3コーナー途中から4コーナーにかけて急な下り坂。直線は平坦。",
        "running_flow": "スタート直後が上り坂のため前半は落ち着きやすく、3コーナー下り坂で加速し、その勢いのまま短い直線に入る流れ。",
        "style_bias": "逃げ・先行が有利。下り坂で加速した前の馬が止まりにくく、差し・追込は物理的に届きにくい。"
      },
      "positive_factors": {
        "single": {
          "post_position": [
            "7枠は単勝回収率123%、複勝回収率123%と高い",
            "4枠は単勝回収率101%と水準以上"
          ],
          "running_style": [
            "逃げは単勝回収率94%〜181%と高く、複勝回収率も優秀"
          ],
          "bloodline": [
            "ロードカナロア産駒は勝率・回収率ともに安定",
            "ファインニードル産駒は単勝回収率が高い",
            "エイシンヒカリ産駒は複勝回収率が高い"
          ],
          "attributes": [],
          "rotation": [],
          "human": [
            "坂井瑠星騎手は勝率20%超、単複回収率100%超",
            "M.デムーロ騎手は単勝回収率200%超",
            "西園正都調教師は単勝回収率205%"
          ],
          "popularity_odds": [
            "5番人気は単勝回収率117%"
          ]
        },
        "composite": [
          {
            "condition": "7枠 × 前走1〜3番人気",
            "reason": "内枠有利と見られがちだが、7枠は回収率が突出しており、前走で上位人気だった実力馬が外からスムーズに加速できる利点が距離ロスを上回るため"
          },
          {
            "condition": "坂井瑠星騎手 × 逃げ・先行",
            "reason": "コース構造上有利な先行馬で高い勝率と回収率を示し、人気馬を確実に勝たせる傾向があるため"
          },
          {
            "condition": "ロードカナロア産駒 × 当日3番人気以内",
            "reason": "最多勝血統だが、特に当日3番人気以内では勝率が高く回収率も安定し、実力が評価された場面で信頼度が高いため"
          }
        ]
      },
      "negative_factors": {
        "single": {
          "post_position": [
            "1枠は単勝回収率34%〜43%と低く過剰人気",
            "8枠は勝率・回収率ともに低迷"
          ],
          "running_style": [
            "追込は勝率約1%、複勝率約7%と低い"
          ],
          "bloodline": [],
          "attributes": [
            "馬体重480kg以上は回収率が低い"
          ],
          "rotation": [
            "中1週以内（2週以下）のローテーションは回収率が極端に低い"
          ],
          "human": [],
          "popularity_odds": []
        },
        "composite": [
          {
            "condition": "1枠 × オッズ30倍以下",
            "reason": "鋭角なコーナーで包まれるリスクが高く、単勝回収率が30〜40%台と低迷し、オッズに見合うリターンが得にくいため"
          },
          {
            "condition": "追込 × 展開待ち",
            "reason": "下り坂で前が止まらない構造上、後方一気は成立しにくく、期待値が構造的に低いため"
          },
          {
            "condition": "馬体重480kg以上 × 中1週以内",
            "reason": "鋭角なコーナーと硬い馬場で大型馬は負担が大きく、間隔が詰まることで疲労回復が間に合わずパフォーマンスを落としやすいため"
          }
        ]
      },
      "meta": {
        "source": "NotebookLM",
        "policy": "original_text_preserved",
        "no_new_conditions_added": true
      }
    },
    {
      "course": {
        "name": "京都芝1400m（内回り）",
        "racecourse": "京都",
        "surface": "芝",
        "distance_m": 1400
      },
      "course_structure": {
        "overview": "向正面2コーナー奥のポケット地点からスタートし、3コーナーまで約516mと長い助走区間がある。4コーナーからゴールまでの直線は328.4m（Aコース）と短く、外回りより70m以上短い。",
        "elevation": "バックストレッチ後半から上り坂が始まり、3コーナーで頂上（高低差3.1m）を迎え、4コーナーにかけて下る山型の高低差構造。",
        "running_flow": "スタート後は隊列が決まりやすいが、3コーナーの上り坂と急な下り坂、鋭角なコーナーによって外を回る馬や逃げ馬が負荷を受けやすい流れ。",
        "style_bias": "短い平坦直線で前は止まりにくいが、単純な逃げ切りよりも、3コーナーで加速し4コーナーで好位インを確保する先行力と器用さが要求される。"
      },
      "positive_factors": {
        "single": {
          "post_position": [
            "3枠は勝率17.8%、単勝回収率200%超と突出",
            "1枠は複勝回収率が高く安定"
          ],
          "running_style": [
            "先行は複勝率・回収率が最も安定",
            "差しは勝率は低いが単勝回収率が高くなるケースがある"
          ],
          "bloodline": [
            "モーリス産駒は成績が良い",
            "ロードカナロア産駒は成績が良い",
            "リオンディーズ産駒は成績が良い",
            "シルバーステート産駒は成績が良い",
            "母父が欧州型ノーザンダンサー系は好走率が高い"
          ],
          "attributes": [],
          "rotation": [
            "前走から100〜200mの距離短縮は単勝回収率118%"
          ],
          "human": [
            "鮫島克駿騎手は回収率・好走率が高い",
            "和田竜二騎手は回収率・好走率が高い"
          ],
          "popularity_odds": []
        },
        "composite": [
          {
            "condition": "3枠 × 先行",
            "reason": "内すぎず包まれにくい位置から鋭角なコーナーをロスなく回れ、コース構造上有利な先行力と組み合わさるため"
          },
          {
            "condition": "距離短縮（100〜200m） × 鮫島克駿または和田竜二騎乗",
            "reason": "距離短縮でペース追走が楽になり脚を溜めやすく、コース得意騎手の騎乗で回収率が100%を超えるため"
          },
          {
            "condition": "牝馬 × キズナ産駒またはエピファネイア産駒",
            "reason": "牝馬戦において中距離指向の血統がタフな内回りでスタミナと底力を活かし、高い回収率を示すため"
          }
        ]
      },
      "negative_factors": {
        "single": {
          "post_position": [
            "8枠は勝率1.4〜4.5%と低く回収率も低迷",
            "2枠は勝率・回収率ともに低迷"
          ],
          "running_style": [
            "逃げは勝率が低く過剰人気になりやすい",
            "追込は物理的に届かず複勝率・回収率が低い"
          ],
          "bloodline": [],
          "attributes": [
            "牝馬で馬体重460kg以上は勝ち切れない傾向"
          ],
          "rotation": [],
          "human": [],
          "popularity_odds": [
            "1番人気は回収率が平均を下回る"
          ]
        },
        "composite": [
          {
            "condition": "8枠 × 人気馬（特に逃げ・先行）",
            "reason": "鋭角なコーナーで距離ロスや脚の消耗を強いられ、構造的に飛ぶ可能性が高いため"
          },
          {
            "condition": "逃げ × 単勝オッズ5倍未満",
            "reason": "逃げ馬は過剰に売れやすいが勝率は6〜8%程度と低く、坂で捕まりやすいため"
          },
          {
            "condition": "牝馬 × 馬体重460kg以上",
            "reason": "器用さに欠け勝ち切れないデータが多く、単系馬券の期待値を下げるため"
          }
        ]
      },
      "meta": {
        "source": "NotebookLM",
        "policy": "original_text_preserved",
        "no_new_conditions_added": true
      }
    },
    {
      "course": {
        "name": "京都芝1400m（外回り）",
        "racecourse": "京都",
        "surface": "芝",
        "distance_m": 1400
      },
      "course_structure": {
        "overview": "向正面の2コーナー出口付近からスタートし、最初のコーナーまで約512mと非常に長い。直線はAコース403.7m、B・C・Dコース398.7m。",
        "elevation": "スタートから約200mは平坦で、そこから3コーナー（淀の坂）に向けて上り勾配が続く。3コーナー頂上から4コーナーにかけて高低差4.3mを一気に下る。最後の直線は平坦。",
        "running_flow": "前半はスローペースになりやすく、3～4コーナーの下り坂で物理的に加速がつき、直線入り口ではトップスピードに近い状態になりやすい。",
        "style_bias": "逃げ・先行が比較的安定するが、クラスが上がると差しが決まりやすくなる傾向がある。下り坂で馬群がばらけやすく直線で差しも届きやすい。持続的な末脚と立ち回りのスムーズさ、瞬発力や下り坂を利用して加速できる器用さが求められる。"
      },
      "positive_factors": {
        "single": {
          "post_position": [
            "4枠・7枠・8枠など中～外枠の回収率が相対的に高い"
          ],
          "running_style": [
            "逃げは回収率が高い（単勝回収率120%超のデータあり）",
            "差しは勝率・連対率が優秀"
          ],
          "bloodline": [
            "キタサンブラック産駒の成績が良い（単勝回収率が高い）",
            "ドゥラメンテ産駒の成績が良い",
            "モーリス産駒の成績が良い",
            "ロードカナロア産駒の成績が良い"
          ],
          "attributes": [
            "馬体重500kg以上の成績・回収率が良い",
            "前走から馬体重が減少している馬の回収率が高い"
          ],
          "rotation": [],
          "human": [
            "松山弘平騎手の回収率が高い",
            "岩田望来騎手の回収率が高い",
            "斎藤新騎手の回収率が高い",
            "鮫島克駿騎手の回収率が高い"
          ],
          "popularity_odds": [
            "10番人気以下や15番人気などの超人気薄が激走するケースがあり、下位人気の回収率が高い"
          ]
        },
        "composite": [
          {
            "condition": "馬体重500kg以上 × 5枠～8枠",
            "reason": "3コーナーからの下り坂で重量のある馬は加速（慣性）を得やすく、外枠なら揉まれずスムーズに加速して直線を向けるため"
          },
          {
            "condition": "前走から馬体重減 × 3枠～8枠",
            "reason": "馬体重減はマイナス評価されがちだが、このコースでは身軽さが急なアップダウンとコーナーワークでプラスに働き、スムーズに加速できるため"
          },
          {
            "condition": "キタサンブラック産駒 × 1勝・2勝クラス",
            "reason": "このコースで勝率・連対率が非常に高く、単勝回収率200%超のデータもあり、下級～中級条件で人気に関わらず高いパフォーマンスを発揮するため"
          },
          {
            "condition": "斎藤新騎手または鮫島克駿騎手 × 穴馬（中位～下位人気）",
            "reason": "両騎手とも単勝回収率・複勝回収率が非常に高く、人気薄を上位に持ってくるケースが多いとされているため"
          }
        ]
      },
      "negative_factors": {
        "single": {
          "post_position": [
            "1枠の勝率・回収率が著しく低い"
          ],
          "running_style": [
            "追込は決まりづらく回収率・好走率ともに低い"
          ],
          "bloodline": [
            "ディープインパクト産駒は2～3着が多く勝ち切れない傾向（単勝回収率が低い場合がある）",
            "ハーツクライ産駒は2～3着が多く勝ち切れない傾向（単勝回収率が低い場合がある）",
            "種牡馬年齢が20歳以上の産駒は不振"
          ],
          "attributes": [
            "種牡馬年齢20歳以上の産駒は不振"
          ],
          "rotation": [
            "前走4コーナー通過順位が9番手以下の馬の回収率が低い"
          ],
          "human": [],
          "popularity_odds": [
            "1番人気は2番人気より勝率が低いケースがあり信頼度が低い"
          ]
        },
        "composite": [
          {
            "condition": "1番人気 × 1枠～2枠",
            "reason": "内枠の勝率が低いにもかかわらず内枠が売れてオッズが辛くなりやすく、1番人気自体の勝率も低調で「飛ぶ可能性が高いのに配当がつかない」ため"
          },
          {
            "condition": "前走4コーナー9番手以下 × 追込",
            "reason": "3角からの下り坂で全馬が加速し、後方から前を捕まえるには能力差が必要で、前走でも後方だった馬が今回だけ位置を上げるのは難しいため"
          },
          {
            "condition": "ディープインパクト・ハーツクライ産駒 × 単勝勝負",
            "reason": "2～3着止まりのケースが多く報告され、人気になりやすいため単勝で狙うと回収率を押し下げる要因となるため"
          },
          {
            "condition": "種牡馬年齢20歳以上 × 高齢馬",
            "reason": "スピードの持続力と瞬発力のバランスが求められるコースで、遺伝的活力や身体的ピークを過ぎた馬は対応できず、回収率が70%を切る消しデータとして機能するため"
          }
        ]
      },
      "meta": {
        "source": "NotebookLM",
        "policy": "original_text_preserved",
        "no_new_conditions_added": true
      }
    },
    {
      "course": {
        "name": "京都芝1600m（内回り）",
        "racecourse": "京都",
        "surface": "芝",
        "distance_m": 1600
      },
      "course_structure": {
        "overview": "第2コーナー奥のポケットからスタートし、第3コーナーまで約700m（Aコース時716.2m）と非常に長い。最後の直線はAコース使用時で328.4mと短く平坦。",
        "elevation": "向正面から第3コーナーにかけて上り（高低差3.1m）、3コーナー途中から4コーナーにかけて下るレイアウト。",
        "running_flow": "スタート後の長い直線で隊列が決まり、3コーナーの坂の下りで加速し、そのまま短い直線になだれ込む流れになりやすい。",
        "style_bias": "逃げ・先行が有利。直線の短さと平坦な構造により後方待機は差し届かないケースが多い。外回りのような瞬発力勝負より、位置取りと下り坂を利用したスピード持続が問われる。"
      },
      "positive_factors": {
        "single": {
          "post_position": [
            "6枠は単勝回収率125%と回収率が高い",
            "7枠は複勝回収率163%～235%と回収率が高い"
          ],
          "running_style": [
            "逃げは単勝回収率173%～252%と高く、複勝回収率も100%を超える"
          ],
          "bloodline": [
            "エピファネイア産駒は複勝率約35%で回収率が安定",
            "キズナ産駒は複勝率約40%",
            "モーリス産駒は単勝回収率100%超"
          ],
          "attributes": [],
          "rotation": [],
          "human": [
            "西村淳也騎手は複勝率40%超で単複回収率100%超",
            "永島まなみ騎手は単勝回収率300%～600%超",
            "浜中俊騎手は単勝回収率約200%"
          ],
          "popularity_odds": [
            "6～9番人気の中穴ゾーンは単勝回収率が100%を超える"
          ]
        },
        "composite": [
          {
            "condition": "中～外枠（5～7枠） × 逃げ・先行",
            "reason": "外枠は嫌われやすいがスタートからコーナーまでが長く外からでも好位を確保しやすい一方、内枠は包まれるリスクが高く回収率が低いため"
          },
          {
            "condition": "西村淳也・永島まなみ・浜中俊騎手 × 単勝オッズ5倍以上（2番人気以下）",
            "reason": "各騎手はこのコースで単勝回収率が100%を大きく超えるデータがあり、人気薄を上位に持ってくる腕とコース適性があるとされているため"
          },
          {
            "condition": "エピファネイア産駒 × 2歳・3歳限定戦",
            "reason": "若駒戦専用コースで仕上がりの早さとスピードの持続力が求められ、エピファネイア産駒は複勝率が高く単複回収率も100%付近またはそれ以上を維持しているため"
          }
        ]
      },
      "negative_factors": {
        "single": {
          "post_position": [
            "1枠は勝率4～5%台で単勝回収率30～50%台と低い",
            "2枠は勝率4～5%台で単勝回収率30～50%台と低い"
          ],
          "running_style": [
            "追込は勝率1%未満～2.9%程度で回収率も非常に低い"
          ],
          "bloodline": [
            "ロードカナロア産駒は単勝回収率57%～70%程度と低い"
          ],
          "attributes": [],
          "rotation": [],
          "human": [],
          "popularity_odds": [
            "1番人気は勝率約26～28%で単勝回収率も60%台"
          ]
        },
        "composite": [
          {
            "condition": "内枠（1～2枠） × 差し・追込",
            "reason": "内枠は包まれやすく直線が短いため一度位置を下げると挽回が物理的に難しく、回収率も低いとされているため"
          },
          {
            "condition": "1番人気 × ロードカナロア産駒",
            "reason": "ロードカナロア産駒は過剰人気になりやすく単勝回収率が50～70%台で伸び悩み、1番人気の信頼度が低い傾向と重なるため"
          },
          {
            "condition": "中内田充正厩舎 × 過剰人気（川田騎手など）",
            "reason": "このコースでは勝ち切れない（2・3着が多い）傾向があり単勝回収率が50%台となるデータがあり、断然人気になりやすいが単勝としての妙味が薄いとされているため"
          }
        ]
      },
      "meta": {
        "source": "NotebookLM",
        "policy": "original_text_preserved",
        "no_new_conditions_added": true
      }
    },
    {
      "course": {
        "name": "京都芝1600m（外回り）",
        "racecourse": "京都",
        "surface": "芝",
        "distance_m": 1600
      },
      "course_structure": {
        "overview": "向正面2コーナー奥のポケット地点からスタートし、最初のコーナーまで約712m（711.7m）と非常に長い。直線はAコース403.7m（B～Dコース398.7m）で、直線に上り坂がなく平坦。",
        "elevation": "高低差4.3m。向正面から3コーナーにかけて上り（淀の坂）、3コーナー頂上から4コーナーにかけて一気に下る。下り坂はコーナー部分のみに存在し、最後の直線は平坦。",
        "running_flow": "序盤はゆったり流れやすいが、3コーナーの下り坂で強制的にペースが上がり、直線入り口ではスピードに乗った状態になりやすい。3〜4コーナーからゴールまで長く速い脚（ロングスパート・持続力）が求められる。",
        "style_bias": "逃げ・先行の勝率・複勝率が高いが、クラスが上がると差しの台頭が目立つ。追い込みは構造的に不利。直線が平坦で前がバテにくい一方、下り坂で加速できる差しは勢いを殺さず直線に入れるが、最後方からの追い込みは届きにくい。"
      },
      "positive_factors": {
        "single": {
          "post_position": [
            "1枠は回収率が高い傾向（単勝回収率113%など）",
            "8枠は回収率が高い傾向（複勝率が高い）"
          ],
          "running_style": [
            "逃げは単勝回収率115%〜208%と高い",
            "先行は回収率が安定",
            "差しは回収率が安定"
          ],
          "bloodline": [
            "イスラボニータ産駒は勝率・回収率が高い（単勝回収率300%超）",
            "ルーラーシップ産駒は高回収率",
            "ハービンジャー産駒は高回収率"
          ],
          "attributes": [],
          "rotation": [
            "前走から距離短縮は回収率が良い",
            "休み明け2戦目（叩き2走目）は回収率90%超と高い"
          ],
          "human": [
            "川田将雅騎手は高回収率",
            "坂井瑠星騎手は高回収率",
            "団野大成騎手は高回収率"
          ],
          "popularity_odds": []
        },
        "composite": [
          {
            "condition": "距離短縮（今回1600m） × 1枠〜6枠",
            "reason": "前走で長い距離を経験している馬は追走が楽になり、下り坂からのロングスパート合戦でスタミナの優位性を発揮しやすく、内目をロスなく立ち回れるため"
          },
          {
            "condition": "イスラボニータ産駒 × 単勝オッズ適正範囲（極端な人気薄以外）",
            "reason": "このコースで勝率60〜70%超、単勝回収率300%超の数値を記録しており、種牡馬の特性（平坦適性・機動力）がコース形状に合致しているため"
          },
          {
            "condition": "休み明け2戦目 × 関西馬",
            "reason": "下り坂での加速には実戦勘が必要で、長期休養明けは不振だが叩き2走目で回収率が跳ね上がる（90%超）。関西圏の騎手・厩舎は坂の使い方を熟知しているとされているため"
          }
        ]
      },
      "negative_factors": {
        "single": {
          "post_position": [
            "3枠は勝率・回収率が極端に低い（勝率1%〜3%台、単勝回収率7%など）"
          ],
          "running_style": [
            "追い込みは勝率・連対率が低く、単勝回収率も低調（40〜50%程度）"
          ],
          "bloodline": [
            "ブラックタイド産駒は複勝率や回収率が低い傾向がある",
            "ドゥラメンテ産駒は複勝率や回収率が低い傾向がある",
            "エピファネイア産駒は複勝率や回収率が低い傾向がある"
          ],
          "attributes": [],
          "rotation": [
            "前走から距離延長（1400m以下から）は勝率・回収率ともに低い",
            "長期休養明け（中15週以上）は不振"
          ],
          "human": [],
          "popularity_odds": [
            "1番人気の信頼度は標準よりやや低い傾向が見られる場合がある"
          ]
        },
        "composite": [
          {
            "condition": "前走1400m以下からの距離延長 × 逃げ・先行",
            "reason": "ペース配分に戸惑い（折り合いを欠く）やすく、下り坂からの持続力勝負でスタミナ切れを起こしやすいとされ、単勝回収率が約59%と低いとされているため"
          },
          {
            "condition": "3枠 × 人気馬（上位人気）",
            "reason": "3枠は勝率1.0%〜3.1%など低い数値が出ており、内枠の恩恵を受けきれず外枠のようにスムーズに加速することも難しい中途半端な位置になりやすく、オッズに見合う勝率を確保できていないため"
          },
          {
            "condition": "長期休養明け（15週以上） × 7-8枠または追い込み",
            "reason": "下り坂での急加速やコーナーリングのレース勘が戻っていないとされ、外枠は距離ロスや遠心力の負荷、追い込みは位置取り面の不利が重なり対応が難しいため"
          }
        ]
      },
      "meta": {
        "source": "NotebookLM",
        "policy": "original_text_preserved",
        "no_new_conditions_added": true
      }
    },
    {
      "course": {
        "name": "京都芝1800m（外回り）",
        "racecourse": "京都",
        "surface": "芝",
        "distance_m": 1800
      },
      "course_structure": {
        "overview": "向正面（2コーナー奥）の引き込み線の最深部ポケットからスタートし、最初のコーナーまで約900m（911.7m）と非常に長い。直線はAコース403.7m（B〜Dコース398.7m）で平坦で広め。",
        "elevation": "3コーナーにかけて約4m（4.3m）の上り坂があり、3コーナー頂上付近から4コーナーにかけて一気に下る「淀の坂」が存在する。",
        "running_flow": "前半はゆったり流れやすく、3コーナーの下り（ラスト4F付近）からペースアップしやすい。直線入り口ではスピードに乗った状態になりやすく、平坦直線でのスピード持続力比べになりやすい。",
        "style_bias": "先行が最も安定し勝率・連対率・複勝率が高い傾向。逃げは目標にされやすく先行に劣る。追込は勝率2.1%程度と苦戦傾向。極端なハイペースによる消耗戦は発生しにくい。"
      },
      "positive_factors": {
        "single": {
          "post_position": [
            "6枠は単勝回収率94%〜214%と高い（集計期間による）",
            "5枠・4枠など中枠は安定して回収率が高い傾向"
          ],
          "running_style": [
            "先行は単勝回収率85%〜118%と優秀"
          ],
          "bloodline": [
            "モーリス産駒は単勝回収率89〜260%（集計期間による）",
            "サトノダイヤモンド産駒は単勝回収率117〜166%",
            "エピファネイア産駒は複勝率が高め",
            "母父ジャングルポケットは単勝回収率高騰例あり",
            "母父ハービンジャーは高回収率"
          ],
          "attributes": [],
          "rotation": [
            "前走1600m（距離延長）組は成績が良く複勝率や連対率の信頼度が高い",
            "昇降級なしは回収率67%と低い"
          ],
          "human": [
            "鮫島克駿騎手は単勝回収率103〜113%",
            "北村友一騎手は単勝回収率96〜119%",
            "C.デムーロ騎手は高勝率かつ高回収",
            "須貝尚介調教師は単勝回収率100%超",
            "高野友和調教師は単勝回収率100%超"
          ],
          "popularity_odds": [
            "2番人気は単勝回収率95〜112%と高い",
            "1番人気は単勝回収率約80%前後"
          ]
        },
        "composite": [
          {
            "condition": "距離延長（前走1600m） × 中枠（4〜6枠）",
            "reason": "前走1600m組はこのコースのスピード能力要求に適性が合致し、中枠（特に5・6枠）は揉まれずスムーズに加速できる利点が加わるため"
          },
          {
            "condition": "モーリス産駒 × 6〜8枠",
            "reason": "このコースで高い単勝回収率を記録し、特に外枠（6〜8枠）で連対率が高い傾向があり、下り坂からのロングスパートと産駒特徴が合致するため"
          },
          {
            "condition": "先行 × 当日2〜4番人気",
            "reason": "1番人気は過剰人気になりがちだが2番人気は単勝回収率が100%を超えるデータがあり、コース構造上有利な先行脚質と組み合わさるため"
          }
        ]
      },
      "negative_factors": {
        "single": {
          "post_position": [
            "1枠は勝率4〜5%台で単勝回収率27〜58%程度と低迷",
            "極端な内枠（1枠など）は回収率が低い"
          ],
          "running_style": [
            "追込は勝率約2〜3%と低く単複回収率も低調",
            "逃げは回収率が先行に劣るケースが見られる"
          ],
          "bloodline": [
            "ルーラーシップ産駒は単勝回収率59%で複勝率も低め",
            "ハーツクライ産駒は回収率が低調"
          ],
          "attributes": [],
          "rotation": [
            "昇降級なしは回収率67%と低い"
          ],
          "human": [],
          "popularity_odds": [
            "1番人気は単勝回収率70〜80%台で過剰投票気味",
            "8番人気以下は勝率1%台以下"
          ]
        },
        "composite": [
          {
            "condition": "1枠 × 差し・追込",
            "reason": "馬群が密集しやすく包まれやすい構造で、後方脚質は下りで外から被されると動けず直線で進路を失うリスクが最大化するため"
          },
          {
            "condition": "ルーラーシップ産駒またはハーツクライ産駒 × 当日1〜3番人気",
            "reason": "このコースで複勝率や回収率が平均を下回るデータがあり、人気に推されると過剰評価となる可能性が高いとされているため"
          },
          {
            "condition": "前走2000m以上（距離短縮） × 8番人気以下",
            "reason": "距離延長（前走1600m）や同距離の方が成績が良い傾向があり、8番人気以下が激走するケースは稀とされ、距離短縮の穴狙いはスピード負けの可能性が高いとされているため"
          }
        ]
      },
      "meta": {
        "source": "NotebookLM",
        "policy": "original_text_preserved",
        "no_new_conditions_added": true
      }
    },
    {
      "course": {
        "name": "京都芝2000m（内回り）",
        "racecourse": "京都",
        "surface": "芝",
        "distance_m": 2000
      },
      "course_structure": {
        "overview": "正面スタンド前、真ん中やや右寄りからスタート。最初のコーナーまで約308.7m（Aコース時）と非常に短い。直線はAコース328.4m、B〜Dコース323.4mで短く平坦。コーナーは4回まわり、半径が小さく小回り。",
        "elevation": "コース全体の高低差は3.1m。向こう正面から上り坂となり3コーナーが頂上。そこから4コーナーにかけて急な下り坂となる「淀の坂」が存在する。",
        "running_flow": "最初のコーナーまでが短く先行争いが激化しやすいが、4つのコーナーの内回りで息が入りやすく、全体の60%がスローペース判定。3コーナーの下り坂（ラスト3F〜4F地点）からペースが上がり、惰性をつけたまま直線へ向かうロングスパート気味の流れになりやすい。",
        "style_bias": "逃げ・先行が有利。差し・追込（特に後方一気）は極めて不利。直線が短く4コーナーで後方にいると届かない。下り坂でペースアップするため外を回すマクリや追い込みは遠心力で外に振られる距離ロスが大きい。"
      },
      "positive_factors": {
        "single": {
          "post_position": [
            "4枠は単勝回収率103〜116%と回収率のピークが見られる",
            "7枠は単勝回収率148.5%と回収率のピークが見られる",
            "1枠は勝率は高いが人気になりやすく回収率は伸び悩みやすい傾向がある"
          ],
          "running_style": [
            "逃げは単勝回収率199.8%などのデータがあり高い",
            "先行は安定して回収率が高い"
          ],
          "bloodline": [
            "ロードカナロアは単勝回収率206%を記録",
            "レイデオロは単勝回収率180%〜471%を記録",
            "キズナは高回収率を記録"
          ],
          "attributes": [
            "前走から馬体重が4kg以上減少した馬の回収率が高い"
          ],
          "rotation": [
            "前走距離が2200m以上の距離短縮組は好走率・回収率ともに高い傾向がある"
          ],
          "human": [
            "武豊は単勝回収率158%を記録",
            "北村友一は単勝回収率163%を記録",
            "川田将雅は勝率・複勝率は抜群だが過剰人気により回収率は100%前後で推移する"
          ],
          "popularity_odds": [
            "6〜9番人気の中穴ゾーンは単勝回収率93〜150%超と高い"
          ]
        },
        "composite": [
          {
            "condition": "前走2200m以上（距離短縮） × 先行",
            "reason": "前走で長い距離を経験している馬はゆったりした流れに戸惑わずスタミナがあるため3コーナーからのロングスパートに対応でき、距離短縮組は距離延長組を上回るとされ、先行と組み合わせることで粘り込みやすいとされているため"
          },
          {
            "condition": "前走比-4kg以上 × 1〜4枠",
            "reason": "一般的に馬体減は嫌われるが、このコースでは絞れた馬体が坂とタイトなコーナーワークでの機動力を高めるとされ、内目の枠で距離ロスなく立ち回れることと組み合わさり、評価と適性のギャップが生まれるとされているため"
          },
          {
            "condition": "武豊 × 3〜5番人気",
            "reason": "武豊はこのコースで高い勝率と複勝率（3番人気以内で60%超）を維持し、単勝回収率150%超のデータもあるとされ、1番人気でなくても勝ち切る技術があると記述されているため"
          }
        ]
      },
      "negative_factors": {
        "single": {
          "post_position": [
            "8枠（大外）は勝率・連対率・回収率のすべてにおいて低調"
          ],
          "running_style": [
            "追込・後方脚質は勝率2%台で複勝率も低く回収率も期待できない"
          ],
          "bloodline": [
            "ハーツクライ系は複勝率は悪くないが単勝回収率が低い傾向がある"
          ],
          "attributes": [],
          "rotation": [
            "前走1800m以下からの距離延長組は短縮組に比べて勝率・回収率が著しく低い"
          ],
          "human": [],
          "popularity_odds": [
            "10番人気以下は勝率ほぼ0%で回収率も壊滅的"
          ]
        },
        "composite": [
          {
            "condition": "前走1800m以下（距離延長） × 8枠",
            "reason": "距離延長馬はスローペースで折り合いを欠くリスクがあり、8枠はコーナー4回で距離ロスが最大となり、スタミナロスと折り合い難が重なるとされているため"
          },
          {
            "condition": "追込（前走4角10番手以下） × 14頭以上",
            "reason": "直線が約328mしかなく後方一気は物理的に間に合わず、多頭数では馬群が密集して外を回す距離ロスや内で詰まるリスクが増大するとされているため"
          },
          {
            "condition": "人気騎手（川田など） × 1枠",
            "reason": "1枠の単勝回収率は低い（61%等のデータあり）とされ過剰人気になりやすく、包まれるリスクもあり、オッズが低い場合はリスク対効果の観点で妙味が薄いとされているため"
          }
        ]
      },
      "meta": {
        "source": "NotebookLM",
        "policy": "original_text_preserved",
        "no_new_conditions_added": true
      }
    },
    {
      "course": {
        "name": "京都芝2200m（外回り）",
        "racecourse": "京都",
        "surface": "芝",
        "distance_m": 2200
      },
      "course_structure": {
        "overview": "正面スタンド前直線、内回りコースの4コーナー出口付近に設置された地点からスタート。最初のコーナーまで約400m（397.3m）。直線はAコース403.7m（B〜Dコース398.7m）で、直線部分はほぼ平坦。スタート後の直線が長く序盤はペースが上がりにくく、3コーナーの下り坂（残り800m付近）からレースが動き出し、ラスト4F（800m）のロングスパート戦になりやすい。",
        "elevation": "向正面半ばから3コーナーにかけて上り坂（高低差4.3m）があり、3コーナーの頂上から4コーナーにかけて下る「淀の坂」が存在する。",
        "running_flow": "スローペースになる確率が約60%と高く、ハイペースは稀（約5%）。3コーナーの下り坂で自然と加速がつき、直線入り口でスピードに乗った状態になりやすい。",
        "style_bias": "極端な逃げ・追込は勝率・複勝率ともに低調。先行は安定感があり連対率が高いが、回収率の観点では差しも優秀な数値を示す。追込は直線だけで一気に追い込む形は間に合わず、逃げは早めにバテて捕まりやすい一方、下り坂を利用して長く脚を使える先行〜差しが有利になりやすい。"
      },
      "positive_factors": {
        "single": {
          "post_position": [
            "1枠は勝率10.9%で成績が良い",
            "8枠は勝率11.6%で成績が良く、単勝回収率119%〜126%と高い"
          ],
          "running_style": [
            "逃げは勝率は低いものの、ハマった時の単勝回収率が高いデータがある（単回147%など）",
            "先行は安定感があり連対率が高い",
            "差しは回収期待値で平均を上回る"
          ],
          "bloodline": [
            "キズナ産駒は単勝回収率115%〜136%と高い回収率を示す",
            "ゴールドシップ産駒は単勝回収率133%〜159%と高い回収率を示す",
            "母父ノーザンダンサー系（特に米国型）を持つ馬の成績・回収率が優秀（例：クロフネ、フレンチデピュティ）"
          ],
          "attributes": [],
          "rotation": [
            "前走から間隔10週以上の馬の回収率が高い傾向がある",
            "前走出遅れがあった馬の回収率が高い傾向がある"
          ],
          "human": [
            "川田将雅は勝率30%超・複勝率70%超で信頼度が高く回収率も100%を超える",
            "岩田望来や団野大成など若手騎手の回収率が高い傾向がある"
          ],
          "popularity_odds": []
        },
        "composite": [
          {
            "condition": "8枠（大外） × スムーズな加速が必要なタイプ（キズナ産駒等）",
            "reason": "8枠は単勝回収率が100%を超えており、3コーナーの下り坂から外目でストレスなく加速して直線の平坦部分になだれ込める物理的利点が働くとされ、キズナ産駒などは揉まれずに能力を全開にしやすく回収率を押し上げると記述されているため"
          },
          {
            "condition": "前走出遅れ × 距離短縮 または 間隔10週以上",
            "reason": "前走出遅れ馬の回収率が100%を超えるとされ、最初のコーナーまで約400mと長く出遅れをリカバリーしやすい構造と記述されている。さらに十分な休養（10週以上）や距離短縮が組み合わさることで期待値が最大化されると記述されているため"
          },
          {
            "condition": "母父ノーザンダンサー系/米国型 × パワー・持続力勝負",
            "reason": "母父にクロフネやフレンチデピュティ等のノーザンダンサー系（特に米国型）を持つ馬の成績・回収率が優秀で、京都2200mが下り坂からのロングスパート合戦という持続力とパワーを要求し、米国血統のスピード持続力が活きると記述されているため（特に人気薄での好走が回収率を支えると記述）"
          }
        ]
      },
      "negative_factors": {
        "single": {
          "post_position": [
            "4枠は勝率4%台、単勝回収率16%〜37%というデータがあり成績が著しく低い"
          ],
          "running_style": [
            "追込は複勝率が低く、単勝回収率も0%〜16%と壊滅的"
          ],
          "bloodline": [
            "エピファネイア産駒は人気になりやすいものの回収率は低め（単回45%〜59%）に出る傾向がある"
          ],
          "attributes": [
            "牡馬混合戦の牝馬は勝率5.0%で単勝回収率54%と低迷"
          ],
          "rotation": [
            "前走1番人気だった馬の回収率が低い傾向がある"
          ],
          "human": [],
          "popularity_odds": []
        },
        "composite": [
          {
            "condition": "混合戦の牝馬 × エリザベス女王杯のイメージによる過剰人気",
            "reason": "牝馬限定G1エリザベス女王杯が行われるコースのため実績のある牝馬が過剰に人気する傾向がある一方、牡馬混合戦での牝馬の成績は著しく低い（勝率約5%）と記述され、人気先行で実益が伴わないとされているため"
          },
          {
            "condition": "4枠（青帽子） × 先行・差し等（脚質不問）",
            "reason": "複数期間データで4枠の勝率・回収率が極端に低いとされ（単勝回収率10%台のデータもあり）、内枠の先行馬を見ながら外から被せられるポケットに入りやすく、下り坂で動けない/位置取りが悪くなるケースが多発すると記述されているため"
          },
          {
            "condition": "前走1番人気 × コース適性未証明",
            "reason": "前走1番人気の馬はこのコースで回収率が低くなる傾向があるとされ、他場でのパフォーマンスだけで人気になっている場合は過剰評価の可能性が高く、京都2200m特有の下り坂からのロングスパートに対応できず人気を裏切るケースが多いと記述されているため"
          }
        ]
      },
      "meta": {
        "source": "NotebookLM",
        "policy": "original_text_preserved",
        "no_new_conditions_added": true
      }
    },
    {
      "course": {
        "name": "京都芝2400m（外回り）",
        "racecourse": "京都",
        "surface": "芝",
        "distance_m": 2400
      },
      "course_structure": {
        "overview": "4コーナー奥のポケット地点からスタート。最初のコーナーまで約600m（597.3m）と非常に長く、直線距離が十分に確保されている。直線の長さはAコース403.7m、B～Dコース398.7mで、4コーナーからゴールまでは平坦。前半は緩み、3コーナーの下り坂を利用してロングスパート（後半3F～4F勝負）になる傾向がある。",
        "elevation": "向こう正面半ばから3コーナーにかけて「淀の坂」を上り（高低差4.3m）、3コーナー頂上から4コーナーにかけて下る構造。直線には坂がない。",
        "running_flow": "スローペースの発生率が71%と極めて高く、ハイペースは8%しかない。前半は緩み、3コーナーの下り坂を利用してロングスパート（後半3F～4F勝負）になる傾向がある。",
        "style_bias": "先行が圧倒的に有利で、勝率・連対率・複勝率の全てで他脚質を上回る。追込は壊滅的で、勝率1.3%・複勝率1.9%（追込）と極めて低く、単勝回収率4.6%・複勝52.4%と記載がある。スタート後の直線が長く隊列がすぐに決まり前半がスローペースになりやすく、後半3コーナーの下り坂でペースが上がるため後方一気は物理的に前を捕まえにくい構造とされる。"
      },
      "positive_factors": {
        "single": {
          "post_position": [
            "4枠の単勝回収率は107～119%と高い傾向がある",
            "7枠の単勝回収率は70～116%と高い傾向がある",
            "偶数馬番の複勝率は34.5%で奇数（20.3%）より高い"
          ],
          "running_style": [
            "先行の単勝回収率が83%～111%と最も高く安定している"
          ],
          "bloodline": [
            "エピファネイアは単勝回収率136%と成績が良い",
            "ディープインパクトは単勝回収率253%（出走数少なめ）と成績が良い",
            "キズナは複勝回収率77%と成績が良い",
            "母父Unbridled's Songは単勝回収率318%と回収率が高い",
            "母父タニノギムレットは単勝回収率180%と回収率が高い"
          ],
          "attributes": [],
          "rotation": [
            "今回距離短縮（前走2600m以上）の単勝回収率が125%と非常に高い"
          ],
          "human": [
            "浜中俊は単勝回収率135～182%と大幅なプラス収支を出している",
            "北村友一は単勝回収率310%と大幅なプラス収支を出している",
            "C.デムーロは単勝回収率204%と大幅なプラス収支を出している"
          ],
          "popularity_odds": [
            "1～3番人気は複勝率50%～80%と信頼度が高いが回収率は平均的",
            "単勝オッズ10～14.9倍の単勝回収率は97.6%と記載がある"
          ]
        },
        "composite": [
          {
            "condition": "距離短縮（前走2600m以上） × 先行脚質",
            "reason": "京都2400mはスローペースになりやすく、長距離戦（2600m以上）を使われてきた馬がスタミナ的な余裕を持ちつつ先行策を取るとそのまま押し切るケースが多発していると記載がある。距離短縮組の単勝回収率が125%で、ここにコース有利な脚質を掛け合わせることで期待値が最大化すると記載がある。"
          },
          {
            "condition": "浜中俊・北村友一・C.デムーロ騎乗 × 4枠または7枠",
            "reason": "このコースで回収率が高い4枠・7枠に入り、回収率が高い騎手（浜中俊・北村友一・C.デムーロなど）の馬は過小評価されがちでも激走する傾向があると記載がある。特に浜中俊は人気馬での信頼度が高く、複合することで軸としての堅実性が増すと記載がある。"
          },
          {
            "condition": "エピファネイア産駒 × 母父米国型（Unbridled's Song等）",
            "reason": "エピファネイア産駒は単勝回収率136%と優秀で、母父に米国型（スピード・パワー）を持つ馬は平坦な京都コースでのスピード勝負に対応しやすく高い回収率を叩き出していると記載がある。"
          }
        ]
      },
      "negative_factors": {
        "single": {
          "post_position": [
            "6枠は勝率3.0～3.6%、単勝回収率28～34%と低調",
            "8枠は単勝回収率26.8%～74%で外枠の中でも特に効率が悪い"
          ],
          "running_style": [
            "追込は単勝回収率0～4.6%と致命的に低い"
          ],
          "bloodline": [],
          "attributes": [
            "道悪（重・不良）では460kg以下の小柄な馬は割引が必要"
          ],
          "rotation": [
            "300～400mの距離延長となる馬は単勝回収率69%と低い"
          ],
          "human": [],
          "popularity_odds": [
            "10番人気以下は勝率0.0%、単勝回収率0%と記載がある",
            "4番人気以下は全体的に好走率が落ちると記載がある"
          ]
        },
        "composite": [
          {
            "condition": "追込脚質 × 6枠または8枠",
            "reason": "追込は物理的に届かないとされ、加えて6枠・8枠はデータ的に死に枠となっているため、人気薄でオッズがついても構造的に好走が極めて困難と記載がある。"
          },
          {
            "condition": "当日4番人気以下 × 距離延長組",
            "reason": "上位人気の信頼度が高いコースで4番人気以下の穴馬は苦戦すると記載がある。距離短縮組が有利な一方で、距離延長組（特に中距離路線からの参戦）はスタミナやペース対応で劣る傾向があり回収率を下げる要因と記載がある。"
          },
          {
            "condition": "道悪（重・不良） × 馬体重460kg以下",
            "reason": "馬場が悪化するとパワーが要求され、データ上、道悪での460kg以下の馬は明確に割引が必要と記載がある。"
          }
        ]
      },
      "meta": {
        "source": "NotebookLM",
        "policy": "original_text_preserved",
        "no_new_conditions_added": true
      }
    },
    {
      "course": {
        "name": "京都ダート1200m",
        "racecourse": "京都",
        "surface": "ダート",
        "distance_m": 1200
      },
      "course_structure": {
        "overview": "スタート地点は向正面の第2コーナー出口付近で、芝スタートではなくダートスタート。最初のコーナーまでの距離は約400m〜410mと長く確保されている。直線の長さは329.1mで、日本のダートコースとしては平均的〜やや短め。スタート後約200mから緩やかな上り坂になり、第3コーナー入口が頂点（高低差約3m）。そこから第4コーナーにかけて一気に下り坂となり、最後の直線は平坦。スタートから最初のコーナーまでの距離が長いため枠順による先行争いの有利不利は発生しにくいものの、3コーナー頂点から4コーナーにかけての下り坂を利用して加速した先行勢が平坦な直線でそのまま雪崩れ込む展開になりやすいとされる。",
        "elevation": "スタート後約200mから緩やかな上り坂になり、第3コーナー入口が頂点（高低差約3m）。そこから第4コーナーにかけて一気に下り坂となり、最後の直線は平坦。",
        "running_flow": "ダート短距離のためハイペース傾向（約54%）だが、最初のコーナーまでの距離が長いため先行争いが激化しすぎず、ミドルペース（約46%）に落ち着くことも多い。クラス別平均勝ち時計は未勝利（1:12.7〜1:13.0）、1勝クラス（1:12.0〜1:12.3）、2勝クラス（1:11.4〜1:11.7）、オープン（1:10.7〜1:10.8）とクラスが上がるごとに明確に速くなる。",
        "style_bias": "逃げ・先行有利で、逃げの勝率は26.9%〜31.1%、先行の勝率は9.6%〜11.0%と高く、複勝率も逃げは50%を超える。追込は勝率1.4%〜1.6%、複勝率5%台と低く届きにくい。3コーナーから4コーナーの下り坂で前に行った馬が加速し、直線が平坦で前が止まりにくく後ろからの逆転が困難とされる。"
      },
      "positive_factors": {
        "single": {
          "post_position": [
            "6枠〜8枠（外枠）の勝率・連対率・複勝率が高い",
            "7枠・8枠は単勝回収率90%〜124%等の高い数値を記録する期間がある"
          ],
          "running_style": [
            "逃げの単勝回収率は163%〜180%と高い",
            "先行でも単勝回収率70%〜80%台と前に行く馬の回収率が安定して高い"
          ],
          "bloodline": [
            "ドレフォンの回収率が高い傾向",
            "シニスターミニスターの回収率が高い傾向",
            "アジアエクスプレスの回収率が高い傾向",
            "ダノンレジェンドの回収率が高い傾向",
            "米国型やストームキャット系の回収率が高い傾向"
          ],
          "attributes": [
            "牡馬の信頼度が高い",
            "セン馬（去勢馬）は単勝回収率116%〜137%と優秀",
            "1勝クラス以上では馬体重520kg以上の大型馬の複勝率が35%前後と安定"
          ],
          "rotation": [
            "前走からの距離短縮（1400mなどからの短縮）組は勝率15.3%・単勝回収率84",
            "同距離組は勝率17.4%・回収率74",
            "短縮組の方が妙味が出る場合がある（同距離優勢の記述もあり解釈に注意が必要）"
          ],
          "human": [
            "田口貫太騎手は単勝回収率98%〜117%と高い回収率を示す",
            "松山弘平騎手は単勝回収率119%〜167%と高い回収率を示す",
            "和田竜二騎手は単勝回収率189%と高い回収率を示す"
          ],
          "popularity_odds": []
        },
        "composite": [
          {
            "condition": "6〜8枠（外枠） × 逃げ・先行脚質",
            "reason": "外枠の馬は揉まれずにスムーズに加速でき、下り坂の勢いを削がれずに直線に向けるためと記載がある。外枠かつ先行できる馬は勝率・回収率ともに最高水準に達すると記載がある。"
          },
          {
            "condition": "前走6番人気以下 × 今回1〜2番人気",
            "reason": "前走大敗や不人気であっても今回上位人気に推されている場合は、勝率34%・単勝回収率135%という高い数値を叩き出していると記載がある。"
          },
          {
            "condition": "大型馬（520kg以上） × 1勝クラス以上 × 外枠",
            "reason": "大型馬は下り坂での加速エネルギーを平坦な直線での推進力に変えやすく、外枠からスムーズに運べた場合の複勝率は35%を超えると記載がある。"
          }
        ]
      },
      "negative_factors": {
        "single": {
          "post_position": [
            "1枠・2枠・5枠の単勝回収率が低い",
            "5枠は勝率はあるものの回収率40%〜50%台と死に枠になりやすい傾向"
          ],
          "running_style": [
            "差しの単勝回収率は53%〜109%とばらつきがある",
            "追込は勝率1%台で回収率0%〜10%台の期間もあり非効率"
          ],
          "bloodline": [
            "ヘニーヒューズ産駒は単勝回収率26%〜38%と過剰人気になりやすく妙味がない"
          ],
          "attributes": [],
          "rotation": [],
          "human": [],
          "popularity_odds": [
            "9番人気前後は勝率0%〜0.4%と極端に低い傾向",
            "10番人気以下の勝率は0.7%〜1.4%程度という記述がある"
          ]
        },
        "composite": [
          {
            "condition": "ヘニーヒューズ産駒 × 人気馬（1〜3番人気）",
            "reason": "ヘニーヒューズ産駒は勝利数は多いが人気になりすぎるため回収率が大幅に低下（単勝回収率30%台）すると記載がある。"
          },
          {
            "condition": "5枠 × 中団・後方待機",
            "reason": "5枠は単勝回収率40〜50%台と低迷し、外から被せられやすく内を見ながらの競馬になり位置取りが中途半端になりがちと記載がある。差し・追込の場合は砂を被って戦意喪失するか届かない位置で終える可能性が高まると記載がある。"
          },
          {
            "condition": "10番人気以下 × 強調材料（外枠・逃げ）なし",
            "reason": "10番人気以下の勝率は0.7%〜1.4%程度と記載があり、強調材料なしで紐に加えると点数が増えるだけで回収率を押し下げる要因となると記載がある。"
          }
        ]
      },
      "meta": {
        "source": "NotebookLM",
        "policy": "original_text_preserved",
        "no_new_conditions_added": true
      }
    },
    {
      "course": {
        "name": "京都ダート1400m",
        "racecourse": "京都",
        "surface": "ダート",
        "distance_m": 1400
      },
      "course_structure": {
        "overview": "芝スタート約150m。最初のコーナーまで約600mと長く、直線は329mで平坦。",
        "elevation": "3コーナー手前から高低差3.0mの上り坂（淀の坂）。3コーナー頂点から4コーナーにかけて下る。直線に坂はない。",
        "running_flow": "芝スタートと長い直線で前半が速くなりやすい。クラスが上がると前傾ラップになりやすい。",
        "style_bias": "逃げ・先行が有利。追込は物理的に届きにくい。"
      },
      "positive_factors": {
        "single": {
          "post_position": [
            "1枠",
            "5枠"
          ],
          "running_style": [
            "逃げ"
          ],
          "bloodline": [
            "シニスターミニスター",
            "ヘニーヒューズ",
            "マジェスティックウォリアー",
            "母父ハーツクライ"
          ],
          "attributes": [
            "5歳馬",
            "関西馬（栗東所属）"
          ],
          "rotation": [],
          "human": [
            "坂井瑠星",
            "団野大成",
            "北村友一"
          ],
          "popularity_odds": []
        },
        "composite": [
          {
            "condition": "坂井瑠星 × 先行（または逃げ）",
            "reason": "スタートセンスと積極的なポジショニングが前有利・スピード優先のコース構造に合致し、高い勝率と単勝回収率を記録しているため。"
          },
          {
            "condition": "シニスターミニスター × 内枠（1～2枠）",
            "reason": "内枠嫌悪によるオッズの歪みが生じやすく、ボールドルーラー系のスピード持続力が内々を回って粘る競馬に適しているため。"
          },
          {
            "condition": "ヘニーヒューズ × 下級条件（未勝利・1勝クラス）",
            "reason": "芝スタートの加速力を活かし、スピードの絶対値で押し切れる条件で回収率が高くなるため。"
          }
        ]
      },
      "negative_factors": {
        "single": {
          "post_position": [
            "3枠",
            "6枠"
          ],
          "running_style": [
            "追込"
          ],
          "bloodline": [
            "ホッコータルマエ",
            "父ロベルト系"
          ],
          "attributes": [
            "関東馬（美浦）",
            "牝馬"
          ],
          "rotation": [],
          "human": [],
          "popularity_odds": [
            "10番人気以下",
            "新馬戦の1番人気"
          ]
        },
        "composite": [
          {
            "condition": "ホッコータルマエ × 全条件",
            "reason": "芝スタートのスピードと平坦直線のキレが求められるコース適性と合致せず、成績が壊滅的であるため。"
          },
          {
            "condition": "1番人気 × 新馬戦",
            "reason": "芝スタートからダートへの切れ目やポケット地点からの合流など不確定要素が多く、回収率が期待できないため。"
          },
          {
            "condition": "追込 × 多頭数（フルゲート）",
            "reason": "3コーナーの坂で前が加速し、直線も平坦なため、展開が向いても物理的に届きにくいため。"
          },
          {
            "condition": "関東馬（美浦） × 中位人気",
            "reason": "輸送リスクやコース経験差により成績が伴わず、妙味が出にくいため。"
          }
        ]
      },
      "meta": {
        "source": "NotebookLM",
        "policy": "original_text_preserved",
        "no_new_conditions_added": true
      }
    },
    {
      "course": {
        "name": "京都ダート1800m",
        "racecourse": "京都",
        "surface": "ダート",
        "distance_m": 1800
      },
      "course_structure": {
        "overview": "スタンド前直線の半ば付近からスタート。最初のコーナーまで約286mと短い。直線は329.1mでゴール前は平坦。全体の高低差は3.0m。",
        "elevation": "向正面半ばから徐々に上り坂、3コーナー入口が「淀の坂」の頂上。そこから4コーナーにかけて一気に下り、直線は平坦。",
        "running_flow": "ハイペースは少なく（約13%）、ミドルペースが約80%。前半と後半が同じくらいのペースになりやすく、中間で緩む傾向。",
        "style_bias": "逃げ・先行が圧倒的に有利。最初のコーナーまでが短くポジション争いが激しい。3～4コーナーが下り坂で前が加速し、直線も短く平坦で追い込みが決まりにくい。"
      },
      "positive_factors": {
        "single": {
          "post_position": [
            "6枠",
            "8枠",
            "3枠〜8枠（オープンクラス以上）",
            "8枠（フルゲート時）"
          ],
          "running_style": [
            "逃げ",
            "先行",
            "マクリ"
          ],
          "bloodline": [
            "シニスターミニスター",
            "キズナ",
            "パイロ",
            "サンダースノー",
            "ミッキーアイル"
          ],
          "attributes": [
            "馬体重500kg以上の大型馬",
            "関西所属騎手"
          ],
          "rotation": [
            "今回距離短縮（キズナ産駒またはミッキーアイル産駒）"
          ],
          "human": [
            "坂井瑠星",
            "松山弘平",
            "岩田望来",
            "田口貫太",
            "C.デムーロ"
          ],
          "popularity_odds": []
        },
        "composite": [
          {
            "condition": "シニスターミニスター産駒 × 2歳・3歳戦",
            "reason": "若駒時代（2歳〜3歳）に回収率と好走率が最大化し、スピードとパワーで押し切る競馬が決まりやすく、単勝・複勝ともにベタ買いでもプラスになる水準の適性を示しているため。"
          },
          {
            "condition": "キズナ産駒 または ミッキーアイル産駒 × 今回距離短縮",
            "reason": "「前走同距離」または「今回距離短縮」のローテーションで回収率が跳ね上がり、芝並みのスピード持続力が活きるコースで、距離短縮で出走してきた際に高い連対率・複勝率を記録し、穴妙味も発生するため。"
          },
          {
            "condition": "オープンクラス以上 × 3枠〜8枠（中〜外枠）",
            "reason": "クラスが上がると馬群が密集しやすく、外からスムーズに加速できる枠順の価値が上がり、包まれるリスクのある内枠よりも期待値が高くなるため。"
          },
          {
            "condition": "フルゲート（16頭立て） × 8枠",
            "reason": "多頭数戦では内枠の馬が揉まれるリスクが極大化し、外からスムーズに自分のリズムで運べる大外枠の「展開利」がオッズ以上に機能するため。"
          },
          {
            "condition": "坂井瑠星騎手 × 2勝クラス以下 × 逃げ・先行馬",
            "reason": "条件戦（2勝クラス以下）で逃げ・先行馬に乗った時の勝率と信頼度が抜群で、人気馬になりやすいが取りこぼしが少ないため。"
          }
        ]
      },
      "negative_factors": {
        "single": {
          "post_position": [
            "7枠",
            "1枠"
          ],
          "running_style": [
            "差し",
            "追込"
          ],
          "bloodline": [
            "ドゥラメンテ",
            "ルーラーシップ",
            "ロードカナロア"
          ],
          "attributes": [
            "馬体重440kg以下の小型馬",
            "4歳馬",
            "牝馬（差し・追込の場合）"
          ],
          "rotation": [],
          "human": [],
          "popularity_odds": [
            "4番人気"
          ]
        },
        "composite": [
          {
            "condition": "馬体重440kg以下 × 内〜中枠",
            "reason": "スタート後のポジション争いで大型馬と接触した際に弾かれやすく、起伏やコーナーでのパワー勝負で劣り、特に内枠で馬群に揉まれると物理的に対抗できないため。"
          },
          {
            "condition": "1番人気馬が8枠 × 1〜4枠の馬",
            "reason": "能力上位の馬が外からスムーズにレースを支配し、内枠の馬は外から被せられて進路を確保できないまま凡走するリスクが高まる構造的な不利が発生するため。"
          },
          {
            "condition": "シニスターミニスター産駒 × 5歳以上",
            "reason": "5歳以降で好走率が急降下し、加齢による能力減退が顕著に出る傾向があり、過去実績や種牡馬イメージで人気になっても期待値を下回りやすいため。"
          },
          {
            "condition": "差し・追込脚質 × 牝馬",
            "reason": "前残りの傾向が強い条件で末脚に賭けるタイプが過剰人気になりやすく、3番人気以内であっても決まりづらい傾向があるため。"
          }
        ]
      },
      "meta": {
        "source": "NotebookLM",
        "policy": "original_text_preserved",
        "no_new_conditions_added": true
      }
    },
    {
      "course": {
        "name": "京都ダート1900m",
        "racecourse": "京都",
        "surface": "ダート",
        "distance_m": 1900
      },
      "course_structure": {
        "overview": "スタート地点は4コーナー出口付近（1800mのスタート地点からさらに100m後方）。最初のコーナーまで約380m〜385m。直線は329.1mで平坦。コース全体の高低差は約3.0m。",
        "elevation": "向こう正面から3コーナー入り口にかけて上り坂。3コーナーから4コーナーにかけて下り坂。最後の直線に坂はなく平坦。",
        "running_flow": "未勝利（約2:01.3）、1勝（約2:00.5）、2勝（約1:59.7）、3勝（約1:59.1）、OP（約1:58.5）。ミドル72%、スロー18%、ハイ11%。1800mに比べてスローになる確率が増える。後半になってもペースが落ちにくく安定した展開になりやすい。",
        "style_bias": "先行が圧倒的に有利、次いで逃げ。差しは割引、追込は壊滅的。3コーナーの坂でペースが動き、下り坂でスピードに乗ったまま平坦直線に入るため前が止まりにくく、追い込みは届きにくい。"
      },
      "positive_factors": {
        "single": {
          "post_position": [
            "1枠",
            "6枠"
          ],
          "running_style": [
            "逃げ",
            "先行",
            "マクリ"
          ],
          "bloodline": [
            "ドレフォン",
            "シニスターミニスター",
            "ホッコータルマエ",
            "ロージズインメイ"
          ],
          "attributes": [
            "3歳馬（古馬混合戦）",
            "5歳馬"
          ],
          "rotation": [
            "芝からダート替わり",
            "距離短縮（500m以上、300-400m）"
          ],
          "human": [
            "坂井瑠星",
            "松山弘平",
            "団野大成",
            "安達昭夫調教師"
          ],
          "popularity_odds": []
        },
        "composite": [
          {
            "condition": "前走芝コース × 1〜4枠（特に1枠）",
            "reason": "内枠は3〜4コーナーの下り坂を最短距離でスムーズに下ることができ、芝で培ったスピードを持続させて直線に向きやすい。内枠から先行できれば砂被りのリスクも軽減され、過小評価されたオッズにより回収率が100%を超えるため。"
          },
          {
            "condition": "3歳馬 × 3歳以上混合戦（古馬混合）",
            "reason": "3歳馬には斤量のアドバンテージがあり、3コーナー手前の長い上り坂で斤量の軽さが登坂エネルギーの負担軽減に直結する。タフな展開になりやすい1900mで斤量利を活かして好走するケースが多く、ベタ買いでもプラスになるほどの期待値が発生するため。"
          },
          {
            "condition": "ドレフォン産駒 × 良馬場または下級条件",
            "reason": "未勝利・1勝クラスや良馬場で複勝率・回収率が跳ね上がり、スピードの持続力が問われるこのコースへの適性が高い。人気になりきらない段階でも走るため、条件とセットで狙うことで期待値が安定するため。"
          },
          {
            "condition": "団野大成騎手 × 中穴人気（3〜6番人気）",
            "reason": "馬のリズムを大切にし終いの脚を確実に伸ばす騎乗スタイルがこのコースに合致し、単勝回収率が非常に高いデータがあるため。人気サイドから少し外れた馬で一発の期待値があるため。"
          }
        ]
      },
      "negative_factors": {
        "single": {
          "post_position": [
            "8枠（大外枠）",
            "5枠"
          ],
          "running_style": [
            "追込"
          ],
          "bloodline": [
            "ナスルーラ系",
            "キングカメハメハ",
            "ハーツクライ（母父含むと低い場合あり）"
          ],
          "attributes": [
            "6歳以上",
            "馬体重460kg未満"
          ],
          "rotation": [
            "前走4コーナー大外回し",
            "前走1700m以下からの延長"
          ],
          "human": [
            "川田将雅"
          ],
          "popularity_odds": [
            "人気になりやすい（8枠）",
            "川田将雅騎手（過剰人気により回収率60%台）"
          ]
        },
        "composite": [
          {
            "condition": "馬齢6歳以上 × 全条件（特に人気馬）",
            "reason": "3コーナー手前から続く長い上り坂と独特のコース変遷への対応力が加齢とともに低下し、データ上6歳以上の回収率が壊滅的で、人気でも物理的な衰えによりパフォーマンスを落とす可能性が極めて高くなるため。"
          },
          {
            "condition": "8枠（大外枠） × 人気サイド",
            "reason": "3コーナーの坂で外を回される距離ロスがスタミナを削ぐ構造になっており、過剰に売れる傾向があるため回収率妙味が薄く危険な人気馬になりやすい条件のため。"
          },
          {
            "condition": "前走4コーナー大外回し × 今回も外枠（または差し脚質）",
            "reason": "不器用さやポジション取りの甘さを示唆し、京都1900mの長い上り坂で再び外を回らされるとスタミナ消耗が致命的となり、平坦直線で失速につながる。構造的に挽回が難しいため。"
          },
          {
            "condition": "川田将雅騎手 × 1〜2番人気",
            "reason": "勝率や複勝率は高いが過剰人気を集め、単勝・複勝回収率が60%台と低水準。2番人気以内でも取りこぼすケースが見られ、馬券的な旨味が消失しているため。"
          }
        ]
      },
      "meta": {
        "source": "NotebookLM",
        "policy": "original_text_preserved",
        "no_new_conditions_added": true
      }
    }
  ]
}
